{
  "memberId": "018e861a-15e1-48cb-994b-018876d54347",
  "memberName": "Mustafa Kaya",
  "type": "İmzası Bulunan Kanun Teklifleri",
  "label": "Bills signed",
  "sourceUrl": "https://www.tbmm.gov.tr/milletvekili/KanunTeklifiUyeninImzasiBulunanTeklifler?ortakDonemId=134155f0-c3d6-4d24-893b-f3a2ef695ae7&Id=018e861a-15e1-48cb-994b-018876d54347",
  "count": 15,
  "records": [
    {
      "section": "Mustafa KAYA İstanbul - YENİ YOL",
      "title": "2/1358",
      "date": "",
      "url": "",
      "fields": {
        "Taksim/ Esas No": "2/1358",
        "Tarihi": "14.07.2023",
        "Kanun Teklifi Başlığı ve Özeti": "Türkiye Cumhuriyeti Emekli Sandığı Kanunu İle Sosyal Sigortalar Ve Genel Sağlık Sigortası Kanununda Değişiklik Yapılmasına İlişkin Kanun Teklifi"
      },
      "englishFields": {
        "Kanun Teklifi Başlığı ve Özeti": "Proposal on Amending the Republic of Türkiye Pension Fund Law and the Social Insurance and General Health Insurance Law"
      }
    },
    {
      "section": "Mustafa KAYA İstanbul - YENİ YOL",
      "title": "2/1734",
      "date": "",
      "url": "",
      "fields": {
        "Taksim/ Esas No": "2/1734",
        "Tarihi": "02.11.2023",
        "Kanun Teklifi Başlığı ve Özeti": "5510 Sayılı Sosyal Sigortalar ve Genel Sağlık Sigortası Kanununda Değişiklik Yapılmasına Dair Kanun Teklifi"
      },
      "englishFields": {
        "Kanun Teklifi Başlığı ve Özeti": "Proposal on Amending the Social Insurance and General Health Insurance Law No. 5510"
      }
    },
    {
      "section": "Mustafa KAYA İstanbul - YENİ YOL",
      "title": "2/2051",
      "date": "",
      "url": "",
      "fields": {
        "Taksim/ Esas No": "2/2051",
        "Tarihi": "29.02.2024",
        "Kanun Teklifi Başlığı ve Özeti": "Hayvanları Koruma Kanununda Değişiklik Yapılmasına Dair Kanun Teklifi"
      },
      "englishFields": {
        "Kanun Teklifi Başlığı ve Özeti": "Bill on Amendments to the Animal Protection Law"
      }
    },
    {
      "section": "Mustafa KAYA İstanbul - YENİ YOL",
      "title": "2/2595",
      "date": "",
      "url": "",
      "fields": {
        "Taksim/ Esas No": "2/2595",
        "Tarihi": "09.10.2024",
        "Kanun Teklifi Başlığı ve Özeti": "Askeralma Kanununda Değişiklik Yapılmasına Dair Kanun Teklifi"
      },
      "englishFields": {
        "Kanun Teklifi Başlığı ve Özeti": "Bill on Amendments to the Military Recruitment Law"
      }
    },
    {
      "section": "Mustafa KAYA İstanbul - YENİ YOL",
      "title": "2/2635",
      "date": "",
      "url": "",
      "fields": {
        "Taksim/ Esas No": "2/2635",
        "Tarihi": "23.10.2024",
        "Kanun Teklifi Başlığı ve Özeti": "Devlet Memurları Kanununda Değişiklik Yapılmasına Dair Kanun Teklifi"
      },
      "englishFields": {
        "Kanun Teklifi Başlığı ve Özeti": "Bill on Amendments to the Civil Servants Law"
      }
    },
    {
      "section": "Mustafa KAYA İstanbul - YENİ YOL",
      "title": "2/2735",
      "date": "",
      "url": "",
      "fields": {
        "Taksim/ Esas No": "2/2735",
        "Tarihi": "29.11.2024",
        "Kanun Teklifi Başlığı ve Özeti": "Sosyal Sigortalar ve Genel Sağlık Sigortası Kanununda Değişiklik Yapılmasına Dair Kanun Teklifi"
      },
      "englishFields": {
        "Kanun Teklifi Başlığı ve Özeti": "Bill on Amendments to the Social Insurance and General Health Insurance Law"
      }
    },
    {
      "section": "Mustafa KAYA İstanbul - YENİ YOL",
      "title": "2/2975",
      "date": "",
      "url": "",
      "fields": {
        "Taksim/ Esas No": "2/2975",
        "Tarihi": "06.03.2025",
        "Kanun Teklifi Başlığı ve Özeti": "İş Kanununda Değişiklik Yapılmasına Dair Kanun Teklifi"
      },
      "englishFields": {
        "Kanun Teklifi Başlığı ve Özeti": "Bill on Amendments to the Labor Law"
      }
    },
    {
      "section": "Mustafa KAYA İstanbul - YENİ YOL",
      "title": "2/3037",
      "date": "",
      "url": "",
      "fields": {
        "Taksim/ Esas No": "2/3037",
        "Tarihi": "26.03.2025",
        "Kanun Teklifi Başlığı ve Özeti": "Engelliler Bakanlığı Kurulmasına Dair Kanun Teklifi"
      },
      "englishFields": {
        "Kanun Teklifi Başlığı ve Özeti": "Proposal for the Establishment of the Ministry of Disabled People"
      }
    },
    {
      "section": "Mustafa KAYA İstanbul - YENİ YOL",
      "title": "2/3100",
      "date": "",
      "url": "",
      "fields": {
        "Taksim/ Esas No": "2/3100",
        "Tarihi": "08.05.2025",
        "Kanun Teklifi Başlığı ve Özeti": "Elektronik Haberleşme Kanununda Değişiklik Yapılmasına Dair Kanun Teklifi"
      },
      "englishFields": {
        "Kanun Teklifi Başlığı ve Özeti": "Bill on Amendments to the Electronic Communications Law"
      }
    },
    {
      "section": "Mustafa KAYA İstanbul - YENİ YOL",
      "title": "2/3176",
      "date": "",
      "url": "",
      "fields": {
        "Taksim/ Esas No": "2/3176",
        "Tarihi": "24.06.2025",
        "Kanun Teklifi Başlığı ve Özeti": "Uyuşturucu ile Mücadele Kanunu Teklifi"
      },
      "englishFields": {
        "Kanun Teklifi Başlığı ve Özeti": "Anti-Drug Law Proposal"
      }
    },
    {
      "section": "Mustafa KAYA İstanbul - YENİ YOL",
      "title": "2/3254",
      "date": "",
      "url": "",
      "fields": {
        "Taksim/ Esas No": "2/3254",
        "Tarihi": "07.08.2025",
        "Kanun Teklifi Başlığı ve Özeti": "İcra ve İflas Kanunu ile Sosyal Sigortalar ve Genel Sağlık Sigortası Kanununda Değişiklik Yapılmasına Dair Kanun Teklifi"
      },
      "englishFields": {
        "Kanun Teklifi Başlığı ve Özeti": "Bill on Amendments to the Enforcement and Bankruptcy Law and the Social Insurance and General Health Insurance Law"
      }
    },
    {
      "section": "Mustafa KAYA İstanbul - YENİ YOL",
      "title": "2/3412",
      "date": "",
      "url": "",
      "fields": {
        "Taksim/ Esas No": "2/3412",
        "Tarihi": "10.12.2025",
        "Kanun Teklifi Başlığı ve Özeti": "Ceza Muhakemesi Kanununda Değişiklik Yapılmasına Dair Kanun Teklifi"
      },
      "englishFields": {
        "Kanun Teklifi Başlığı ve Özeti": "Bill on Amendments to the Criminal Procedure Code"
      }
    },
    {
      "section": "Mustafa KAYA İstanbul - YENİ YOL",
      "title": "2/3490",
      "date": "",
      "url": "",
      "fields": {
        "Taksim/ Esas No": "2/3490",
        "Tarihi": "22.01.2026",
        "Kanun Teklifi Başlığı ve Özeti": "Yurt Dışı Seçim Bölgesi Kurulmasına Dair Kanun Teklifi"
      },
      "englishFields": {
        "Kanun Teklifi Başlığı ve Özeti": "Bill on the Establishment of Overseas Electoral Regions"
      }
    },
    {
      "section": "Mustafa KAYA İstanbul - YENİ YOL",
      "title": "2/3528",
      "date": "",
      "url": "",
      "fields": {
        "Taksim/ Esas No": "2/3528",
        "Tarihi": "11.02.2026",
        "Kanun Teklifi Başlığı ve Özeti": "Diyanet İşleri Başkanlığı Kuruluş ve Görevleri Hakkında Kanunda Değişiklik Yapılmasına Dair Kanun Teklifi"
      },
      "englishFields": {
        "Kanun Teklifi Başlığı ve Özeti": "Proposal to Amend the Law on the Establishment and Duties of the Presidency of Religious Affairs"
      }
    },
    {
      "section": "Mustafa KAYA İstanbul - YENİ YOL",
      "title": "2/3529",
      "date": "",
      "url": "",
      "fields": {
        "Taksim/ Esas No": "2/3529",
        "Tarihi": "12.02.2026",
        "Kanun Teklifi Başlığı ve Özeti": "Yükseköğretim Kanununda Değişiklik Yapılmasına Dair Kanun Teklifi"
      },
      "englishFields": {
        "Kanun Teklifi Başlığı ve Özeti": "Bill on Amendments to the Higher Education Law"
      }
    }
  ]
}