{
  "memberId": "28643cef-ae5b-43c7-8323-01887af767eb",
  "memberName": "Seyithan İzsiz",
  "type": "İmzası Bulunan Kanun Teklifleri",
  "label": "Bills signed",
  "sourceUrl": "https://www.tbmm.gov.tr/milletvekili/KanunTeklifiUyeninImzasiBulunanTeklifler?ortakDonemId=134155f0-c3d6-4d24-893b-f3a2ef695ae7&Id=28643cef-ae5b-43c7-8323-01887af767eb",
  "count": 4,
  "records": [
    {
      "section": "Seyithan İZSİZ İstanbul - AK Parti",
      "title": "2/3119",
      "date": "",
      "url": "",
      "fields": {
        "Taksim/ Esas No": "2/3119",
        "Tarihi": "16.05.2025",
        "Kanun Teklifi Başlığı ve Özeti": "Bazı Kanun ve Kanun Hükmünde Kararnamelerde Değişiklik Yapılmasına Dair Kanun Teklifi"
      },
      "englishFields": {
        "Kanun Teklifi Başlığı ve Özeti": "Bill on Amendments to Certain Laws and Decree Laws"
      }
    },
    {
      "section": "Seyithan İZSİZ İstanbul - AK Parti",
      "title": "2/3138",
      "date": "",
      "url": "",
      "fields": {
        "Taksim/ Esas No": "2/3138",
        "Tarihi": "23.05.2025",
        "Kanun Teklifi Başlığı ve Özeti": "Karayolları Trafik Kanununda Değişiklik Yapılmasına Dair Kanun Teklifi"
      },
      "englishFields": {
        "Kanun Teklifi Başlığı ve Özeti": "Bill on Amendments to the Highway Traffic Law"
      }
    },
    {
      "section": "Seyithan İZSİZ İstanbul - AK Parti",
      "title": "2/3160",
      "date": "",
      "url": "",
      "fields": {
        "Taksim/ Esas No": "2/3160",
        "Tarihi": "16.06.2025",
        "Kanun Teklifi Başlığı ve Özeti": "Türk Parasının Kıymetini Koruma Hakkında Kanun ve Bazı Kanunlarda Değişiklik Yapılmasına Dair Kanun Teklifi"
      },
      "englishFields": {
        "Kanun Teklifi Başlığı ve Özeti": "Proposal on Amending the Law on the Protection of the Value of Turkish Currency and Some Laws"
      }
    },
    {
      "section": "Seyithan İZSİZ İstanbul - AK Parti",
      "title": "2/3174",
      "date": "",
      "url": "",
      "fields": {
        "Taksim/ Esas No": "2/3174",
        "Tarihi": "24.06.2025",
        "Kanun Teklifi Başlığı ve Özeti": "Sağlıkla İlgili Bazı Kanunlarda ve 663 Sayılı Kanun Hükmünde Kararnamede Değişiklik Yapılmasına Dair Kanun Teklifi"
      },
      "englishFields": {
        "Kanun Teklifi Başlığı ve Özeti": "Bill on Amendments to Certain Health-Related Laws and Decree Law No. 663"
      }
    }
  ]
}