{
  "memberId": "f72877c2-d9a4-037b-e050-007f01005610",
  "memberName": "Yunus Emre",
  "type": "İmzası Bulunan Genel Görüşme Önergeleri",
  "label": "General debate motions signed",
  "sourceUrl": "https://www.tbmm.gov.tr/milletvekili/UyeninImzasiBulunanGenelGorusmeOnergeleri?ortakDonemId=134155f0-c3d6-4d24-893b-f3a2ef695ae7&Id=f72877c2-d9a4-037b-e050-007f01005610",
  "count": 6,
  "records": [
    {
      "section": "Yunus EMRE İstanbul - CHP",
      "title": "8/6",
      "date": "",
      "url": "https://www.tbmm.gov.tr/Denetim/Genel-Gorusme-Onergesi-Detay/68e0fcbd-0300-46ae-a144-018948d09ef1",
      "fields": {
        "Dönem": "28",
        "Taksim/ Esas No": "8/6",
        "Tarihi": "11-07-2023",
        "Önergenin Başlığı ve Özeti": "Suriyeli sığınmacıların ülkelerine dönüşü için Suriye yönetimiyle anlaşma yoluna gidilmesi konusunun ele alınması amacıyla bir genel görüşme açılmasına ilişkin önergesi"
      },
      "englishFields": {
        "Önergenin Başlığı ve Özeti": "Motion to open a general meeting to discuss the issue of reaching an agreement with the Syrian administration for the return of Syrian refugees to their country."
      }
    },
    {
      "section": "Yunus EMRE İstanbul - CHP",
      "title": "8/25",
      "date": "",
      "url": "https://www.tbmm.gov.tr/Denetim/Genel-Gorusme-Onergesi-Detay/d8d488e4-b122-441d-98d0-018d7e3fad4c",
      "fields": {
        "Dönem": "28",
        "Taksim/ Esas No": "8/25",
        "Tarihi": "02-02-2024",
        "Önergenin Başlığı ve Özeti": "Emekli vatandaşların ekonomik sorunlarının görüşülmesi ve çözüm üretilmesi amacıyla bir genel görüşme açılmasına ilişkin önergesi"
      },
      "englishFields": {
        "Önergenin Başlığı ve Özeti": "Motion to open a general meeting to discuss the economic problems of retired citizens and find solutions"
      }
    },
    {
      "section": "Yunus EMRE İstanbul - CHP",
      "title": "8/95",
      "date": "",
      "url": "https://www.tbmm.gov.tr/Denetim/Genel-Gorusme-Onergesi-Detay/eef0c4dd-d120-4a8d-81f7-019a261b110a",
      "fields": {
        "Dönem": "28",
        "Taksim/ Esas No": "8/95",
        "Tarihi": "22-10-2025",
        "Önergenin Başlığı ve Özeti": "Türk futbolunun genel sorunları ile yabancı oyuncu transferlerinin görüşülmesi ve alınabilecek önlemlerin belirlenmesi amacıyla bir genel görüşme açılmasına ilişkin önergesi"
      },
      "englishFields": {
        "Önergenin Başlığı ve Özeti": "Motion to open a general meeting to discuss the general problems of Turkish football and foreign player transfers and to determine the measures that can be taken."
      }
    },
    {
      "section": "Yunus EMRE İstanbul - CHP",
      "title": "8/122",
      "date": "",
      "url": "https://www.tbmm.gov.tr/Denetim/Genel-Gorusme-Onergesi-Detay/22bed5de-c739-4c85-9c0b-019db9164dc3",
      "fields": {
        "Dönem": "28",
        "Taksim/ Esas No": "8/122",
        "Tarihi": "17-04-2026",
        "Önergenin Başlığı ve Özeti": "Kırsal bölgelerde yürütülen jeotermal arama ve sondaj faaliyetlerinin mera alanları, tarımsal üretim ve hayvancılık üzerindeki etkileri konusunda bir genel görüşme açılmasına ilişkin önergesi"
      },
      "englishFields": {
        "Önergenin Başlığı ve Özeti": "Proposal to open a general discussion on the effects of geothermal exploration and drilling activities carried out in rural areas on pasture lands, agricultural production and livestock."
      }
    },
    {
      "section": "Yunus EMRE İstanbul - CHP",
      "title": "8/126",
      "date": "",
      "url": "https://www.tbmm.gov.tr/Denetim/Genel-Gorusme-Onergesi-Detay/1a7030ec-9d51-4f2b-9a89-019e88680dd7",
      "fields": {
        "Dönem": "28",
        "Taksim/ Esas No": "8/126",
        "Tarihi": "12-05-2026",
        "Önergenin Başlığı ve Özeti": "Hakkında siyasal casusluk iddiası bulunan bir kişinin daha önceki görevlendirmeleri konusunda bir genel görüşme açılmasına ilişkin önergesi"
      },
      "englishFields": {
        "Önergenin Başlığı ve Özeti": "Motion of a person accused of political espionage to open a general discussion regarding his previous assignments"
      }
    },
    {
      "section": "Yunus EMRE İstanbul - CHP",
      "title": "8/133",
      "date": "",
      "url": "https://www.tbmm.gov.tr/Denetim/Genel-Gorusme-Onergesi-Detay/43ff90cf-a939-488f-bc69-019ed0afa941",
      "fields": {
        "Dönem": "28",
        "Taksim/ Esas No": "8/133",
        "Tarihi": "11-06-2026",
        "Önergenin Başlığı ve Özeti": "Demokratik siyasi hayata ve seçim güvenliğine etki ettiği iddia edilen bazı kararların değerlendirilmesi amacıyla bir genel görüşme açılmasına ilişkin önergesi"
      },
      "englishFields": {
        "Önergenin Başlığı ve Özeti": "Motion to open a general debate to evaluate some decisions that are claimed to affect democratic political life and election security"
      }
    }
  ]
}