{
  "memberId": "f72877c2-d9d4-037b-e050-007f01005610",
  "memberName": "Özgür Özel",
  "type": "İlk İmza Sahibi Olduğu Kanun Teklifleri",
  "label": "Bills where first signatory",
  "sourceUrl": "https://www.tbmm.gov.tr/milletvekili/KanunTeklifiUyeIlkImzaSahibiTeklifleri?ortakDonemId=134155f0-c3d6-4d24-893b-f3a2ef695ae7&Id=f72877c2-d9d4-037b-e050-007f01005610",
  "count": 28,
  "records": [
    {
      "section": "Özgür ÖZEL Manisa - CHP",
      "title": "2/1236",
      "date": "",
      "url": "",
      "fields": {
        "Taksim/ Esas No": "2/1236",
        "Tarihi": "27.09.2018",
        "Kanun Teklifi Başlığı ve Özeti": "Özelleştirilen Şeker Fabrikalarının Kamulaştırılması Hakkındaki Kanun Teklifi"
      },
      "englishFields": {
        "Kanun Teklifi Başlığı ve Özeti": "Bill on Nationalization of Privatized Sugar Factories"
      }
    },
    {
      "section": "Özgür ÖZEL Manisa - CHP",
      "title": "2/1237",
      "date": "",
      "url": "",
      "fields": {
        "Taksim/ Esas No": "2/1237",
        "Tarihi": "25.12.2018",
        "Kanun Teklifi Başlığı ve Özeti": "4046 Sayılı Özelleştirme Uygulamaları Hakkında Kanunda Değişiklik Yapılmasına Dair Kanun Teklifi"
      },
      "englishFields": {
        "Kanun Teklifi Başlığı ve Özeti": "Proposal on Amending the Law No. 4046 on Privatization Practices"
      }
    },
    {
      "section": "Özgür ÖZEL Manisa - CHP",
      "title": "2/1238",
      "date": "",
      "url": "",
      "fields": {
        "Taksim/ Esas No": "2/1238",
        "Tarihi": "17.07.2019",
        "Kanun Teklifi Başlığı ve Özeti": "Radyo ve Televizyon Kuruluş ve Yayın Hizmetleri Hakkında Kanunda Değişiklik Yapılmasına Dair Kanun Teklifi"
      },
      "englishFields": {
        "Kanun Teklifi Başlığı ve Özeti": "Proposal to Amend the Law on Radio and Television Establishment and Broadcasting Services"
      }
    },
    {
      "section": "Özgür ÖZEL Manisa - CHP",
      "title": "2/1239",
      "date": "",
      "url": "",
      "fields": {
        "Taksim/ Esas No": "2/1239",
        "Tarihi": "30.07.2019",
        "Kanun Teklifi Başlığı ve Özeti": "Siyasi Ahlaksızlıkla Mücadele ve Siyasi Etik Kanunu Teklifi"
      },
      "englishFields": {
        "Kanun Teklifi Başlığı ve Özeti": "Proposal for a Law on Combating Political Immorality and Political Ethics"
      }
    },
    {
      "section": "Özgür ÖZEL Manisa - CHP",
      "title": "2/1240",
      "date": "",
      "url": "",
      "fields": {
        "Taksim/ Esas No": "2/1240",
        "Tarihi": "02.08.2019",
        "Kanun Teklifi Başlığı ve Özeti": "Belediye Kanununda Değişiklik Yapılmasına Dair Kanun Teklifi"
      },
      "englishFields": {
        "Kanun Teklifi Başlığı ve Özeti": "Bill on Amendments to the Municipality Law"
      }
    },
    {
      "section": "Özgür ÖZEL Manisa - CHP",
      "title": "2/1241",
      "date": "",
      "url": "",
      "fields": {
        "Taksim/ Esas No": "2/1241",
        "Tarihi": "07.10.2019",
        "Kanun Teklifi Başlığı ve Özeti": "Türkiye Büyük Millet Meclisi İçtüzüğünde Değişiklik Yapılmasına Dair İçtüzük Teklifi"
      },
      "englishFields": {
        "Kanun Teklifi Başlığı ve Özeti": "Internal Regulation Proposal for Amendments to the Internal Regulations of the Grand National Assembly of Türkiye"
      }
    },
    {
      "section": "Özgür ÖZEL Manisa - CHP",
      "title": "2/1242",
      "date": "",
      "url": "",
      "fields": {
        "Taksim/ Esas No": "2/1242",
        "Tarihi": "31.10.2019",
        "Kanun Teklifi Başlığı ve Özeti": "Türkiye Büyük Millet Meclisi İçtüzüğünde Değişiklik Yapılmasına Dair İçtüzük Teklifi"
      },
      "englishFields": {
        "Kanun Teklifi Başlığı ve Özeti": "Internal Regulation Proposal for Amendments to the Internal Regulations of the Grand National Assembly of Türkiye"
      }
    },
    {
      "section": "Özgür ÖZEL Manisa - CHP",
      "title": "2/1243",
      "date": "",
      "url": "",
      "fields": {
        "Taksim/ Esas No": "2/1243",
        "Tarihi": "16.10.2020",
        "Kanun Teklifi Başlığı ve Özeti": "31/5/2006 Tarihli ve 5510 Sayılı Sosyal Sigortalar ve Genel Sağlık Sigortası Kanununda Değişiklik Yapılmasına Dair Kanun Teklifi"
      },
      "englishFields": {
        "Kanun Teklifi Başlığı ve Özeti": "Proposal on Amending the Social Insurance and General Health Insurance Law No. 5510, dated 31/5/2006"
      }
    },
    {
      "section": "Özgür ÖZEL Manisa - CHP",
      "title": "2/1244",
      "date": "",
      "url": "",
      "fields": {
        "Taksim/ Esas No": "2/1244",
        "Tarihi": "24.01.2022",
        "Kanun Teklifi Başlığı ve Özeti": "5237 Sayılı Türk Ceza Kanununda Değişiklik Yapılmasına Dair Kanun Teklifi"
      },
      "englishFields": {
        "Kanun Teklifi Başlığı ve Özeti": "Bill on Amendments to the Turkish Penal Code No. 5237"
      }
    },
    {
      "section": "Özgür ÖZEL Manisa - CHP",
      "title": "2/1245",
      "date": "",
      "url": "",
      "fields": {
        "Taksim/ Esas No": "2/1245",
        "Tarihi": "14.02.2022",
        "Kanun Teklifi Başlığı ve Özeti": "2464 Sayılı Belediye Gelirleri Kanununda Değişiklik Yapılmasına Dair Kanun Teklifi"
      },
      "englishFields": {
        "Kanun Teklifi Başlığı ve Özeti": "Proposal on Amending the Municipal Revenues Law No. 2464"
      }
    },
    {
      "section": "Özgür ÖZEL Manisa - CHP",
      "title": "2/1246",
      "date": "",
      "url": "",
      "fields": {
        "Taksim/ Esas No": "2/1246",
        "Tarihi": "25.03.2022",
        "Kanun Teklifi Başlığı ve Özeti": "Türkiye Varlık Fonu Yönetimi Anonim Şirketinin Kurulması İle Bazı Kanunlarda Değişiklik Yapılmasına Dair Kanunda Değişiklik Yapılmasına Dair Kanun Teklifi"
      },
      "englishFields": {
        "Kanun Teklifi Başlığı ve Özeti": "Bill on Amendments to the Law Concerning the Establishment of the Türkiye Wealth Fund Management Joint Stock Company and Amendments to Certain Laws"
      }
    },
    {
      "section": "Özgür ÖZEL Manisa - CHP",
      "title": "2/1247",
      "date": "",
      "url": "",
      "fields": {
        "Taksim/ Esas No": "2/1247",
        "Tarihi": "29.03.2022",
        "Kanun Teklifi Başlığı ve Özeti": "İş Kanunu ile Bazı Kanunlarda Değişiklik Yapılması Hakkında Kanun Teklifi"
      },
      "englishFields": {
        "Kanun Teklifi Başlığı ve Özeti": "Bill on Amendments to the Labor Law and Some Laws"
      }
    },
    {
      "section": "Özgür ÖZEL Manisa - CHP",
      "title": "2/1248",
      "date": "",
      "url": "",
      "fields": {
        "Taksim/ Esas No": "2/1248",
        "Tarihi": "25.07.2022",
        "Kanun Teklifi Başlığı ve Özeti": "Türk Ceza Kanunu ile Ateşli Silahlar ve Bıçaklar ile Diğer Aletler Hakkında Kanunda Değişiklik Yapılmasına Dair Kanun Teklifi"
      },
      "englishFields": {
        "Kanun Teklifi Başlığı ve Özeti": "Proposal to Amend the Turkish Penal Code and the Law on Firearms, Knives and Other Tools"
      }
    },
    {
      "section": "Özgür ÖZEL Manisa - CHP",
      "title": "2/1249",
      "date": "",
      "url": "",
      "fields": {
        "Taksim/ Esas No": "2/1249",
        "Tarihi": "30.11.2022",
        "Kanun Teklifi Başlığı ve Özeti": "İş Kanununda Değişiklik Yapılmasına Dair Kanun Teklifi"
      },
      "englishFields": {
        "Kanun Teklifi Başlığı ve Özeti": "Bill on Amendments to the Labor Law"
      }
    },
    {
      "section": "Özgür ÖZEL Manisa - CHP",
      "title": "2/1250",
      "date": "",
      "url": "",
      "fields": {
        "Taksim/ Esas No": "2/1250",
        "Tarihi": "26.12.2022",
        "Kanun Teklifi Başlığı ve Özeti": "Kamu Görevlileri Sendikaları ve Toplu Sözleşme Kanunu ile Sosyal Sigortalar ve Genel Sağlık Sigortası Kanununda Değişiklik Yapılmasına Dair Kanun Teklifi"
      },
      "englishFields": {
        "Kanun Teklifi Başlığı ve Özeti": "Bill on Amendments to the Public Servants' Unions and Collective Agreement Law and the Social Insurance and General Health Insurance Law"
      }
    },
    {
      "section": "Özgür ÖZEL Manisa - CHP",
      "title": "2/1251",
      "date": "",
      "url": "",
      "fields": {
        "Taksim/ Esas No": "2/1251",
        "Tarihi": "26.01.2023",
        "Kanun Teklifi Başlığı ve Özeti": "Sendikalar ve Toplu İş Sözleşmesi Kanununda Değişiklik Yapılmasına Dair Kanun Teklifi"
      },
      "englishFields": {
        "Kanun Teklifi Başlığı ve Özeti": "Bill on Amendments to the Law on Trade Unions and Collective Bargaining Agreements"
      }
    },
    {
      "section": "Özgür ÖZEL Manisa - CHP",
      "title": "2/1252",
      "date": "",
      "url": "",
      "fields": {
        "Taksim/ Esas No": "2/1252",
        "Tarihi": "04.04.2023",
        "Kanun Teklifi Başlığı ve Özeti": "Kahramanmaraş Merkezli Depremlerin Yol Açtığı Zararların Giderilmesi ile Bazı Kanun ve Kanun Hükmünde Kararnamelerde Değişiklik Yapılmasına İlişkin Kanun Teklifi"
      },
      "englishFields": {
        "Kanun Teklifi Başlığı ve Özeti": "Proposal on the Elimination of Damages Caused by Kahramanmaraş Centered Earthquakes and Amending Some Laws and Decree Laws"
      }
    },
    {
      "section": "Özgür ÖZEL Manisa - CHP",
      "title": "2/1359",
      "date": "",
      "url": "",
      "fields": {
        "Taksim/ Esas No": "2/1359",
        "Tarihi": "18.10.2022",
        "Kanun Teklifi Başlığı ve Özeti": "Ulusal Bayram ve Genel Tatiller Hakkında Kanunda Değişiklik Yapılmasına Dair Kanun Teklifi"
      },
      "englishFields": {
        "Kanun Teklifi Başlığı ve Özeti": "Proposal on Amending the Law on National Holidays and General Holidays"
      }
    },
    {
      "section": "Özgür ÖZEL Manisa - CHP",
      "title": "2/1787",
      "date": "",
      "url": "",
      "fields": {
        "Taksim/ Esas No": "2/1787",
        "Tarihi": "22.11.2023",
        "Kanun Teklifi Başlığı ve Özeti": "5510 Sayılı Sosyal Sigortalar ve Genel Sağlık Sigortası Kanununda Değişiklik Yapılması Hakkında Kanun Teklifi"
      },
      "englishFields": {
        "Kanun Teklifi Başlığı ve Özeti": "Bill on Amendments to the Social Insurance and General Health Insurance Law No. 5510"
      }
    },
    {
      "section": "Özgür ÖZEL Manisa - CHP",
      "title": "2/1786",
      "date": "",
      "url": "",
      "fields": {
        "Taksim/ Esas No": "2/1786",
        "Tarihi": "22.11.2023",
        "Kanun Teklifi Başlığı ve Özeti": "Sosyal Sigortalar Kanunu, Tarım İşçileri Sosyal Sigortalar Kanunu, Türkiye Cumhuriyeti Emekli Sandığı Kanunu ile Esnaf ve Sanatkarlar ve Diğer Bağımsız Çalışanlar Sosyal Sigortalar Kurumu Kanununda Değişiklik Yapılması Hakkında Kanun Teklifi"
      },
      "englishFields": {
        "Kanun Teklifi Başlığı ve Özeti": "Proposal on Amending the Social Insurance Law, Agricultural Workers Social Insurance Law, Republic of Turkey Retirement Fund Law and the Tradesmen, Craftsmen and Other Self-Employed Social Insurance Institution Law."
      }
    },
    {
      "section": "Özgür ÖZEL Manisa - CHP",
      "title": "2/1788",
      "date": "",
      "url": "",
      "fields": {
        "Taksim/ Esas No": "2/1788",
        "Tarihi": "22.11.2023",
        "Kanun Teklifi Başlığı ve Özeti": "Gelir Vergisi Kanunu ile Bazı Kanunlarda Değişiklik Yapılmasına Dair Kanun Teklifi"
      },
      "englishFields": {
        "Kanun Teklifi Başlığı ve Özeti": "Bill on Amendments to the Income Tax Law and Some Laws"
      }
    },
    {
      "section": "Özgür ÖZEL Manisa - CHP",
      "title": "2/2702",
      "date": "",
      "url": "",
      "fields": {
        "Taksim/ Esas No": "2/2702",
        "Tarihi": "21.11.2024",
        "Kanun Teklifi Başlığı ve Özeti": "Belediye Kanununda Değişiklik Yapılmasına İlişkin Kanun Teklifi"
      },
      "englishFields": {
        "Kanun Teklifi Başlığı ve Özeti": "Bill on Amendments to the Municipality Law"
      }
    },
    {
      "section": "Özgür ÖZEL Manisa - CHP",
      "title": "2/3188",
      "date": "",
      "url": "",
      "fields": {
        "Taksim/ Esas No": "2/3188",
        "Tarihi": "30.06.2025",
        "Kanun Teklifi Başlığı ve Özeti": "Asgari Ücretin Artırılması ile Sigorta Primlerinin İşveren Hisselerinin Bir Kısmının Hazine Tarafından Karşılanmasına Yönelik Sosyal Sigortalar ve Genel Sağlık Sigortası Kanununda Değişiklik Yapılmasına Dair Kanun Teklifi"
      },
      "englishFields": {
        "Kanun Teklifi Başlığı ve Özeti": "Proposal on Amending the Social Insurance and General Health Insurance Law to Increase the Minimum Wage and to Cover a Part of the Employer's Share of Insurance Premiums by the Treasury"
      }
    },
    {
      "section": "Özgür ÖZEL Manisa - CHP",
      "title": "2/3189",
      "date": "",
      "url": "",
      "fields": {
        "Taksim/ Esas No": "2/3189",
        "Tarihi": "30.06.2025",
        "Kanun Teklifi Başlığı ve Özeti": "Sosyal Sigortalar Ve Genel Sağlık Sigortası Kanununda Değişiklik Yapılmasına Dair Kanun Teklifi"
      },
      "englishFields": {
        "Kanun Teklifi Başlığı ve Özeti": "Bill on Amendments to the Social Insurance and General Health Insurance Law"
      }
    },
    {
      "section": "Özgür ÖZEL Manisa - CHP",
      "title": "2/3332",
      "date": "",
      "url": "",
      "fields": {
        "Taksim/ Esas No": "2/3332",
        "Tarihi": "21.10.2025",
        "Kanun Teklifi Başlığı ve Özeti": "Nadir Toprak Elementlerinin Ülke Yararına Kullanılmasına Dair Kanun Teklifi"
      },
      "englishFields": {
        "Kanun Teklifi Başlığı ve Özeti": "Law Proposal on the Use of Rare Earth Elements for the Benefit of the Country"
      }
    },
    {
      "section": "Özgür ÖZEL Manisa - CHP",
      "title": "2/3408",
      "date": "",
      "url": "",
      "fields": {
        "Taksim/ Esas No": "2/3408",
        "Tarihi": "05.12.2025",
        "Kanun Teklifi Başlığı ve Özeti": "Asgari Ücretin Artırılması ile Sigorta Primlerinin İşveren Hisselerinin Bir Kısmının Hazine Tarafından Karşılanmasına Yönelik Sosyal Sigortalar ve Genel Sağlık Sigortası Kanununda Değişiklik Yapılmasına Dair Kanun Teklifi"
      },
      "englishFields": {
        "Kanun Teklifi Başlığı ve Özeti": "Proposal on Amending the Social Insurance and General Health Insurance Law to Increase the Minimum Wage and to Cover a Part of the Employer's Share of Insurance Premiums by the Treasury"
      }
    },
    {
      "section": "Özgür ÖZEL Manisa - CHP",
      "title": "2/3409",
      "date": "",
      "url": "",
      "fields": {
        "Taksim/ Esas No": "2/3409",
        "Tarihi": "05.12.2025",
        "Kanun Teklifi Başlığı ve Özeti": "Asgari Ücret Tespit Komisyonu Kurulması ve İşleyişi Hakkında Kanun Teklifi"
      },
      "englishFields": {
        "Kanun Teklifi Başlığı ve Özeti": "Bill on the Establishment and Functioning of the Minimum Wage Determination Commission"
      }
    },
    {
      "section": "Özgür ÖZEL Manisa - CHP",
      "title": "2/3768",
      "date": "",
      "url": "",
      "fields": {
        "Taksim/ Esas No": "2/3768",
        "Tarihi": "03.07.2026",
        "Kanun Teklifi Başlığı ve Özeti": "Asgari Ücretin Artırılması ile Sigorta Primlerinin İşveren Hisselerinin Bir Kısmının Hazine Tarafından Karşılanmasına Yönelik Sosyal Sigortalar ve Genel Sağlık Sigortası Kanununda Değişiklik Yapılmasına Dair Kanun Teklifi"
      },
      "englishFields": {
        "Kanun Teklifi Başlığı ve Özeti": "Proposal on Amending the Social Insurance and General Health Insurance Law to Increase the Minimum Wage and to Cover a Part of the Employer's Share of Insurance Premiums by the Treasury"
      }
    }
  ]
}